dictionary/__init__.py
dictionary/dictionary.py
CI_CD_Homework_Dictionary_dgndds-2.0.5.dist-info/METADATA
CI_CD_Homework_Dictionary_dgndds-2.0.5.dist-info/WHEEL
CI_CD_Homework_Dictionary_dgndds-2.0.5.dist-info/top_level.txt
CI_CD_Homework_Dictionary_dgndds-2.0.5.dist-info/RECORD
