Metadata-Version: 2.1
Name: CI-CD-Homework-Dictionary-dgndds
Version: 2.0.5
Summary: UNKNOWN
Author: Muhammed Doğancan Yılmazoğlu
License: UNKNOWN
Platform: UNKNOWN
Requires-Python: >=3.8
Requires-Dist: requests (>=2.23.0)
